pytest_stf/__init__.py
pytest_stf/plugin.py
pytest_stf-0.8.0.dist-info/METADATA
pytest_stf-0.8.0.dist-info/WHEEL
pytest_stf-0.8.0.dist-info/entry_points.txt
pytest_stf-0.8.0.dist-info/top_level.txt
pytest_stf-0.8.0.dist-info/RECORD
