Metadata-Version: 2.1
Name: pytest-stf
Version: 0.8.0
Summary: pytest plugin for openSTF
Home-page: https://github.com/opentmi/pytest-stf
Author: Jussi Vatjus-Anttila
Author-email: jussiva@gmail.com
License: Mozilla Public License 2.0 (MPL 2.0)
Keywords: py.test pytest openstf android phone
Classifier: Framework :: Pytest
Classifier: Intended Audience :: Developers
Classifier: License :: OSI Approved :: Mozilla Public License 2.0 (MPL 2.0)
Classifier: Operating System :: POSIX
Classifier: Operating System :: Microsoft :: Windows
Classifier: Operating System :: MacOS :: MacOS X
Classifier: Topic :: Software Development :: Quality Assurance
Classifier: Topic :: Software Development :: Testing
Classifier: Topic :: Utilities
Classifier: Programming Language :: Python
Classifier: Programming Language :: Python :: 3
Classifier: Programming Language :: Python :: 3.9
Classifier: Programming Language :: Python :: 3.10
Classifier: Programming Language :: Python :: 3.11
Classifier: Programming Language :: Python :: 3.12
Classifier: Programming Language :: Python :: 3 :: Only
Requires-Python: >=3.9
Requires-Dist: pytest>=5.0
Requires-Dist: pytest-metadata
Requires-Dist: stf-appium-client~=0.12.0
Requires-Dist: pytest-lockable~=0.11.0
Provides-Extra: dev
Requires-Dist: pytest-cov; extra == "dev"
Requires-Dist: mock; extra == "dev"
Requires-Dist: flake8; extra == "dev"
Requires-Dist: pylint; extra == "dev"
Requires-Dist: pyinstaller; extra == "dev"
